djcompoundqueryset
